{
    "Ar36": {
        "error": 0.0006892475899553609, 
        "filter_outliers_dict": {
            "filter_outliers": true, 
            "iterations": 1, 
            "std_devs": 2
        }, 
        "fit": "Parabolic", 
        "value": 0.07001629392236966
    }, 
    "Ar37": {
        "error": 0.015539705049605152, 
        "filter_outliers_dict": {
            "filter_outliers": true, 
            "iterations": 1, 
            "std_devs": 2
        }, 
        "fit": "linear", 
        "value": -0.013269356487451502
    }, 
    "Ar38": {
        "error": 0.01763387982275394, 
        "filter_outliers_dict": {
            "filter_outliers": true, 
            "iterations": 1, 
            "std_devs": 2
        }, 
        "fit": "linear", 
        "value": 0.057105289173947436
    }, 
    "Ar39": {
        "error": 0.0296639971066978, 
        "filter_outliers_dict": {
            "filter_outliers": true, 
            "iterations": 1, 
            "std_devs": 2
        }, 
        "fit": "Parabolic", 
        "value": 9.556039049902429
    }, 
    "Ar40": {
        "error": 0.05803057197656959, 
        "filter_outliers_dict": {
            "filter_outliers": true, 
            "iterations": 1, 
            "std_devs": 2
        }, 
        "fit": "Parabolic", 
        "value": 338.5956797532285
    }
}